{
  "Main": {
    "body": {
      "type": "Slices",
      "fieldset": "Slice zone",
      "config": {
        "labels": null,
        "choices": {
          "hero_business": {
            "type": "Slice",
            "fieldset": "hero_business",
            "description": "hero business",
            "icon": "face",
            "display": "list",
            "non-repeat": {
              "title": {
                "type": "StructuredText",
                "config": {
                  "single": "heading1,strong,em",
                  "label": "title"
                }
              },
              "subtitle": {
                "type": "StructuredText",
                "config": {
                  "multi": "paragraph",
                  "label": "subtitle"
                }
              }
            },
            "repeat": {}
          },
          "hero_enterprise": {
            "type": "Slice",
            "fieldset": "hero_enterprise",
            "description": "hero enterprise",
            "icon": "face",
            "display": "list",
            "non-repeat": {
              "title": {
                "type": "StructuredText",
                "config": {
                  "single": "heading1,strong,em",
                  "label": "title"
                }
              },
              "subtitle": {
                "type": "StructuredText",
                "config": {
                  "multi": "paragraph",
                  "label": "subtitle"
                }
              }
            },
            "repeat": {}
          },
          "partners": {
            "type": "Slice",
            "fieldset": "partners",
            "description": "partners",
            "icon": "face",
            "display": "list",
            "non-repeat": {
              "title": {
                "type": "StructuredText",
                "config": {
                  "single": "heading3",
                  "label": "title"
                }
              }
            },
            "repeat": {
              "logotype": {
                "type": "Image",
                "config": {
                  "constraint": {},
                  "thumbnails": [],
                  "label": "logotype"
                }
              }
            }
          },
          "questions": {
            "type": "Slice",
            "fieldset": "questions",
            "description": "questions",
            "icon": "face",
            "display": "list",
            "non-repeat": {
              "title": {
                "type": "StructuredText",
                "config": {
                  "single": "heading2,strong",
                  "label": "title"
                }
              }
            },
            "repeat": {
              "title": {
                "type": "StructuredText",
                "config": {
                  "single": "heading3",
                  "label": "title"
                }
              },
              "content": {
                "type": "StructuredText",
                "config": {
                  "multi": "paragraph,strong,hyperlink,image,list-item,o-list-item,o-list-item",
                  "label": "content"
                }
              },
              "link": {
                "type": "Link",
                "config": {
                  "allowTargetBlank": true,
                  "label": "link",
                  "select": null
                }
              },
              "scan": {
                "type": "Boolean",
                "config": {
                  "default_value": false,
                  "label": "scan"
                }
              }
            }
          },
          "contactus": {
            "type": "Slice",
            "fieldset": "contactus",
            "description": "contactus",
            "icon": "face",
            "display": "list",
            "non-repeat": {
              "subtitle": {
                "type": "StructuredText",
                "config": {
                  "single": "paragraph",
                  "label": "subtitle"
                }
              },
              "buttontext": {
                "type": "StructuredText",
                "config": {
                  "single": "paragraph",
                  "label": "buttontext"
                }
              },
              "buttonlink": {
                "type": "StructuredText",
                "config": {
                  "single": "paragraph",
                  "label": "buttonlink"
                }
              }
            },
            "repeat": {}
          },
          "packagesfeatures": {
            "type": "Slice",
            "fieldset": "packagesfeatures",
            "description": "packages features",
            "icon": "add_to_photos",
            "display": "list",
            "non-repeat": {
              "title": {
                "type": "StructuredText",
                "config": {
                  "single": "heading3",
                  "label": "title"
                }
              }
            },
            "repeat": {
              "featuretitle": {
                "type": "StructuredText",
                "config": {
                  "single": "heading4",
                  "label": "feature title"
                }
              },
              "unlimitedstatus": {
                "type": "StructuredText",
                "config": {
                  "single": "paragraph",
                  "label": "unlimited status"
                }
              },
              "businessstatus": {
                "type": "StructuredText",
                "config": {
                  "multi": "paragraph,preformatted,heading1,heading2,heading3,heading4,heading5,heading6,strong,em,hyperlink,image,embed,list-item,o-list-item,rtl",
                  "label": "business status"
                }
              },
              "enterprisestatus": {
                "type": "StructuredText",
                "config": {
                  "single": "paragraph",
                  "label": "enterprise status"
                }
              },
              "growth_status": {
                "type": "StructuredText",
                "config": {
                  "multi": "paragraph",
                  "label": "Growth status"
                }
              },
              "free_status": {
                "type": "StructuredText",
                "config": {
                  "multi": "paragraph",
                  "label": "free status"
                }
              },
              "more_plans": {
                "type": "StructuredText",
                "config": {
                  "multi": "paragraph, preformatted, heading1, heading2, heading3, heading4, heading5, heading6, strong, em, hyperlink, image, embed, list-item, o-list-item, rtl",
                  "label": "more plans",
                  "placeholder": "more plans (put disabled here)"
                }
              }
            }
          },
          "tariffplans": {
            "type": "Slice",
            "fieldset": "tariffplans",
            "description": "tariff plan",
            "icon": "attach_money",
            "display": "list",
            "non-repeat": {
              "widget_currency_billing_title": {
                "type": "StructuredText",
                "config": {
                  "multi": "paragraph,preformatted,heading1,heading2,heading3,heading4,heading6,strong,em,hyperlink,image,embed,list-item,o-list-item,rtl",
                  "label": "Widget Currency Billing Title",
                  "placeholder": "Billing widget title"
                }
              },
              "monthlyperiodtogglelabel": {
                "type": "StructuredText",
                "config": {
                  "single": "paragraph",
                  "label": "MonthlyPeriodToggleLabel"
                }
              },
              "anualperiodtogglelabel": {
                "type": "StructuredText",
                "config": {
                  "multi": "paragraph",
                  "label": "AnnualPeriodToggleLabel"
                }
              },
              "currencydropdownlabel": {
                "type": "StructuredText",
                "config": {
                  "multi": "paragraph",
                  "label": "CurrencyDropdownLabel"
                }
              },
              "all_plans_support": {
                "type": "StructuredText",
                "config": {
                  "multi": "paragraph",
                  "label": "All plans Support",
                  "placeholder": "All plans Support"
                }
              },
              "enterprisecondition": {
                "type": "StructuredText",
                "config": {
                  "multi": "paragraph",
                  "label": "EnterpriseCondition"
                }
              },
              "monthlycondition": {
                "type": "StructuredText",
                "config": {
                  "single": "paragraph",
                  "label": "Monthly condition"
                }
              },
              "annualcondition": {
                "type": "StructuredText",
                "config": {
                  "single": "paragraph",
                  "label": "Annual condition"
                }
              },
              "enterprisebuttontext": {
                "type": "StructuredText",
                "config": {
                  "single": "paragraph",
                  "label": "EnterpriseButtonText"
                }
              },
              "enterprisebuttonlink": {
                "type": "Link",
                "config": {
                  "label": "EnterpriseButtonLink",
                  "select": null
                }
              },
              "buttontext": {
                "type": "StructuredText",
                "config": {
                  "multi": "paragraph",
                  "label": "button text"
                }
              },
              "buttonbaselink": {
                "type": "Link",
                "config": {
                  "label": "button base link",
                  "select": null
                }
              },
              "annualcoefficient": {
                "type": "Number",
                "config": {
                  "label": "Annual coefficient"
                }
              },
              "firstlawtitle": {
                "type": "StructuredText",
                "config": {
                  "single": "paragraph",
                  "label": "first law title"
                }
              },
              "firstlawlocation": {
                "type": "StructuredText",
                "config": {
                  "single": "paragraph",
                  "label": "first law location"
                }
              },
              "secondlawtitle": {
                "type": "StructuredText",
                "config": {
                  "single": "paragraph",
                  "label": "second law title"
                }
              },
              "secondlawlocation": {
                "type": "StructuredText",
                "config": {
                  "single": "paragraph",
                  "label": "second law location"
                }
              },
              "thirdlawtitle": {
                "type": "StructuredText",
                "config": {
                  "single": "paragraph",
                  "label": "third law title"
                }
              },
              "thirdlawlocation": {
                "type": "StructuredText",
                "config": {
                  "single": "paragraph",
                  "label": "third law location"
                }
              }
            },
            "repeat": {
              "plantitle": {
                "type": "StructuredText",
                "config": {
                  "single": "heading3",
                  "label": "plan title"
                }
              },
              "plandescription": {
                "type": "StructuredText",
                "config": {
                  "single": "paragraph,strong,em",
                  "label": "plan description"
                }
              },
              "plan_benefits": {
                "type": "StructuredText",
                "config": {
                  "multi": "paragraph",
                  "label": "plan_benefits",
                  "placeholder": "plan benefits"
                }
              },
              "oneprivacypriceusd": {
                "type": "Number",
                "config": {
                  "label": "one privacy price usd"
                }
              },
              "twoprivacypriceusd": {
                "type": "Number",
                "config": {
                  "label": "two privacy price usd"
                }
              },
              "threeprivacypriceusd": {
                "type": "Number",
                "config": {
                  "label": "three privacy price usd"
                }
              },
              "oneprivacypriceeur": {
                "type": "Number",
                "config": {
                  "label": "one privacy price eur"
                }
              },
              "twoprivacypriceeur": {
                "type": "Number",
                "config": {
                  "label": "two privacy price eur"
                }
              },
              "threeprivacypriceeur": {
                "type": "Number",
                "config": {
                  "label": "three privacy price eur"
                }
              },
              "bottom_clarification": {
                "type": "StructuredText",
                "config": {
                  "multi": "paragraph",
                  "label": "Bottom clarification"
                }
              },
              "check_features_on_card": {
                "type": "StructuredText",
                "config": {
                  "multi": "strong,list-item",
                  "label": "Check features on card",
                  "placeholder": "features inside main card for 3 plans"
                }
              }
            }
          },
          "widget_slider_with_plans": {
            "type": "Slice",
            "fieldset": "Widget Slider with plans",
            "description": "Widget Slider with plans",
            "icon": "slideshow",
            "display": "list",
            "non-repeat": {},
            "repeat": {
              "law_image": {
                "type": "Image",
                "config": {
                  "constraint": {
                    "width": 50,
                    "height": 50
                  },
                  "thumbnails": [],
                  "label": "Law_image"
                }
              },
              "law_text": {
                "type": "StructuredText",
                "config": {
                  "multi": "preformatted,heading1,heading2,heading3,heading4,heading5,heading6,strong,em,hyperlink,image,embed,list-item,o-list-item,rtl",
                  "label": "law text"
                }
              }
            }
          },
          "bussiness_enterprise_toggle": {
            "type": "Slice",
            "fieldset": "bussiness enterprise toggle",
            "description": "bussiness enterprise toggle",
            "icon": "business_center",
            "display": "list",
            "non-repeat": {},
            "repeat": {
              "business_toggle": {
                "type": "StructuredText",
                "config": {
                  "multi": "paragraph",
                  "label": "business toggle"
                }
              },
              "enterprise_toggle": {
                "type": "StructuredText",
                "config": {
                  "multi": "paragraph",
                  "label": "enterprise toggle"
                }
              }
            }
          }
        }
      }
    }
  },
  "SEO": {
    "uid": {
      "type": "UID",
      "config": {
        "label": "UID",
        "placeholder": "Add UID, for example: pricing"
      }
    },
    "metatitle": {
      "type": "StructuredText",
      "config": {
        "multi": "paragraph",
        "label": "Meta title",
        "placeholder": "Add metatitle, up to 60 characters recommended"
      }
    },
    "metadescription": {
      "type": "StructuredText",
      "config": {
        "multi": "paragraph",
        "label": "Meta description",
        "placeholder": "Add meta description, up to 160 characters recommended"
      }
    },
    "canonical": {
      "type": "StructuredText",
      "config": {
        "multi": "paragraph",
        "label": "Canonical URL",
        "placeholder": "Add canonical URL, for example: https://secureprivacy.ai/pricing"
      }
    }
  }
}
